pygard/__init__.py
pygard/client/__init__.py
pygard/client/client.py
pygard/config/__init__.py
pygard/config/config.py
pygard/core/__init__.py
pygard/core/base_service.py
pygard/core/connection.py
pygard/core/logger.py
pygard/models/__init__.py
pygard/models/common.py
pygard/models/request.py
pygard/models/response.py
pygard/models/entity/__init__.py
pygard/models/entity/gard.py
pygard/models/entity/geometry.py
pygard/models/entity/sheet.py
pygard/services/__init__.py
pygard/services/gard_service.py
pygard/services/geometry_service.py
pygard/services/sheet_service.py
pygard/utils/__init__.py
pygard/utils/exceptions.py
pygard-0.1.3.dist-info/METADATA
pygard-0.1.3.dist-info/WHEEL
pygard-0.1.3.dist-info/top_level.txt
pygard-0.1.3.dist-info/RECORD
