Metadata-Version: 2.4
Name: pygard
Version: 0.1.3
Summary: A modern async Python client for Gard data service
Author-email: qm <qingmu_0722@163.com>
Classifier: Development Status :: 3 - Alpha
Classifier: Intended Audience :: Developers
Classifier: License :: OSI Approved :: MIT License
Classifier: Programming Language :: Python :: 3
Classifier: Programming Language :: Python :: 3.8
Classifier: Programming Language :: Python :: 3.9
Classifier: Programming Language :: Python :: 3.10
Classifier: Programming Language :: Python :: 3.11
Classifier: Programming Language :: Python :: 3.12
Requires-Python: >=3.8
Requires-Dist: aiohttp>=3.8.0
Requires-Dist: pydantic>=2.0.0
Requires-Dist: pydantic-settings>=2.0.0
Requires-Dist: structlog>=23.0.0
Requires-Dist: typing-extensions>=4.0.0
Requires-Dist: dataclasses-json>=0.6.0
Requires-Dist: pytest>=8.3.5
Requires-Dist: pip>=25.0.1
Requires-Dist: setuptools>=75.3.2
Requires-Dist: pytest-asyncio>=0.24.0
Requires-Dist: jupyter>=1.1.1
Requires-Dist: notebook>=7.3.3
Requires-Dist: nest-asyncio>=1.6.0
Requires-Dist: build>=1.2.2.post1
Requires-Dist: twine>=6.1.0
Requires-Dist: pandas>=2.0.3
Requires-Dist: geopandas>=0.13.2
Requires-Dist: shapely>=2.0.7
Requires-Dist: alibabacloud-oss-v2>=1.1.2
Requires-Dist: matplotlib>=3.7.5
Requires-Dist: detritalpy>=1.4.3
Requires-Dist: psycopg2-binary>=2.9.10
Provides-Extra: dev
Requires-Dist: pytest>=7.0.0; extra == "dev"
Requires-Dist: pytest-asyncio>=0.21.0; extra == "dev"
Requires-Dist: pytest-cov>=4.0.0; extra == "dev"
Requires-Dist: black>=23.0.0; extra == "dev"
Requires-Dist: isort>=5.12.0; extra == "dev"
Requires-Dist: mypy>=1.0.0; extra == "dev"
Requires-Dist: ruff>=0.1.0; extra == "dev"
